{"commitInfo":{"timestamp":1780150341128,"userId":"78204234866761","userName":"sarthakag2002@gmail.com","operation":"WRITE","operationParameters":{"mode":"Overwrite","statsOnLoad":false,"partitionBy":"[]"},"notebook":{"notebookId":"3374614679376481"},"queryHistoryStatementId":"d2edfa5f-83cc-4760-acb0-5de761b64ae7","clusterId":"0530-134502-oaf34fro-v2n","isolationLevel":"WriteSerializable","isBlindAppend":false,"operationMetrics":{"numFiles":"1","numRemovedFiles":"0","numRemovedBytes":"0","numDeletionVectorsRemoved":"0","numOutputRows":"11","numOutputBytes":"1948"},"tags":{"noRowsCopied":"true","restoresDeletedRows":"false"},"engineInfo":"Databricks-Runtime/18.1.x-aarch64-photon-scala2.13","txnId":"1e2efa07-d36d-417a-ad5b-6aa60799ef49"}}
{"metaData":{"id":"e1869224-3a57-47e2-a6f0-9e2ca9ee3f6f","format":{"provider":"parquet","options":{}},"schemaString":"{\"type\":\"struct\",\"fields\":[{\"name\":\"delivery_city\",\"type\":\"string\",\"nullable\":true,\"metadata\":{}},{\"name\":\"total_orders\",\"type\":\"long\",\"nullable\":true,\"metadata\":{}},{\"name\":\"customers\",\"type\":\"long\",\"nullable\":true,\"metadata\":{}},{\"name\":\"total_revenue\",\"type\":\"double\",\"nullable\":true,\"metadata\":{}},{\"name\":\"avg_order_value\",\"type\":\"double\",\"nullable\":true,\"metadata\":{}}]}","partitionColumns":[],"configuration":{"delta.enableDeletionVectors":"true"},"createdTime":1780150339842}}
{"protocol":{"minReaderVersion":3,"minWriterVersion":7,"readerFeatures":["deletionVectors"],"writerFeatures":["deletionVectors","appendOnly","invariants"]}}
{"add":{"path":"part-00000-a45d09f3-5cb4-44ab-85fc-2a70977ee44b.c000.snappy.parquet","partitionValues":{},"size":1948,"modificationTime":1780150341000,"dataChange":true,"stats":"{\"numRecords\":11,\"minValues\":{\"delivery_city\":\"AHEMDABAD\",\"total_orders\":394,\"customers\":328,\"total_revenue\":287518.41,\"avg_order_value\":671.05},\"maxValues\":{\"delivery_city\":\"PUNE\",\"total_orders\":486,\"customers\":392,\"total_revenue\":353072.96,\"avg_order_value\":760.02},\"nullCount\":{\"delivery_city\":0,\"total_orders\":0,\"customers\":0,\"total_revenue\":0,\"avg_order_value\":0},\"tightBounds\":true}","tags":{"INSERTION_TIME":"1780150341000000","MIN_INSERTION_TIME":"1780150341000000","MAX_INSERTION_TIME":"1780150341000000","OPTIMIZE_TARGET_SIZE":"268435456"}}}
